Metadata-Version: 1.0
Name: distributions-dk
Version: 0.1
Summary: Gaussian distributions
Home-page: UNKNOWN
Author: Deirdre Kong
Author-email: deirdre.y.kong@gmail.com
License: UNKNOWN
Platform: UNKNOWN
